<?xml version="1.0" encoding="windows-1252"?>

<stadium id="league2_2" name="Weißbierstadion">
  <terrain id="terrain1"/>
  <lawn quality="12"/>
  <goals id="aluminumgoals" wooden="true" aluminum="true"/>
  <careerstandblocks/>
  <careeradboardblocks/>
  <stands maxspectators="2120">
    <stand id="stage2_normal" modification="stage2_normal">
      <position x="0.0" y="0.0" z="35.0"/>
      <rotation x="0.0" y="0.0" z="0.0"/>
    </stand>
    <stand id="stage2_normal" modification="stage2_normal">
      <position x="-20.0" y="0.0" z="35.0"/>
      <rotation x="0.0" y="0.0" z="0.0"/>
    </stand>
    <stand id="stage2_normal" modification="stage2_normal">
      <position x="20.0" y="0.0" z="35.0"/>
      <rotation x="0.0" y="0.0" z="0.0"/>
    </stand>
    <stand id="stage1_normal" modification="stage1_normal_stairs_m">
      <position x="0.0" y="0.0" z="-25.0"/>
      <rotation x="0.0" y="180.0" z="0.0"/>
    </stand>
    <stand id="stage3_normal" modification="stage3_normal_roof1">
      <position x="20.0" y="0.0" z="45.0"/>
      <rotation x="0.0" y="0.0" z="0.0"/>
    </stand>
    <stand id="stage3_normal" modification="stage3_normal_roof1">
      <position x="0.0" y="0.0" z="45.0"/>
      <rotation x="0.0" y="0.0" z="0.0"/>
    </stand>
    <stand id="stage3_normal" modification="stage3_normal_roof1">
      <position x="-20.0" y="0.0" z="45.0"/>
      <rotation x="0.0" y="0.0" z="0.0"/>
    </stand>
    <stand id="stage1_normal" modification="stage1_normal_entrance1">
      <position x="0.0" y="0.0" z="25.0"/>
      <rotation x="0.0" y="0.0" z="0.0"/>
    </stand>
    <stand id="stage1_normal" modification="stage1_normal_banister">
      <position x="-20.0" y="0.0" z="25.0"/>
      <rotation x="0.0" y="0.0" z="0.0"/>
    </stand>
    <stand id="stage2_normal" modification="stage2_normal_banister">
      <position x="-10.0" y="0.0" z="-35.0"/>
      <rotation x="0.0" y="180.0" z="0.0"/>
    </stand>
    <stand id="stage2_normal" modification="stage2_normal_banister">
      <position x="10.0" y="0.0" z="-35.0"/>
      <rotation x="0.0" y="180.0" z="0.0"/>
    </stand>
    <stand id="stage2_completion" modification="stage2_completion_round_stairs_banister_l">
      <position x="30.0" y="0.0" z="-35.0"/>
      <rotation x="0.0" y="270.0" z="0.0"/>
    </stand>
    <stand id="stage2_completion" modification="stage2_completion_round_stairs_banister_r">
      <position x="-30.0" y="0.0" z="-35.0"/>
      <rotation x="0.0" y="90.0" z="0.0"/>
    </stand>
    <stand id="stage1_curve" modification="stage1_curve_banister">
      <position x="35.0" y="0.0" z="-25.0"/>
      <rotation x="0.0" y="90.0" z="0.0"/>
    </stand>
    <stand id="stage1_normal" modification="stage1_normal_banister">
      <position x="20.0" y="0.0" z="-25.0"/>
      <rotation x="0.0" y="180.0" z="0.0"/>
    </stand>
    <stand id="stage1_normal" modification="stage1_normal_banister">
      <position x="-20.0" y="0.0" z="-25.0"/>
      <rotation x="0.0" y="180.0" z="0.0"/>
    </stand>
    <stand id="stage1_curve" modification="stage1_curve_banister">
      <position x="-35.0" y="0.0" z="-25.0"/>
      <rotation x="0.0" y="180.0" z="0.0"/>
    </stand>
    <stand id="stage1_curve" modification="stage1_curve_banister">
      <position x="-35.0" y="0.0" z="25.0"/>
      <rotation x="0.0" y="270.0" z="0.0"/>
    </stand>
    <stand id="stage1_normal" modification="stage1_normal_banister">
      <position x="35.0" y="0.0" z="-10.0"/>
      <rotation x="0.0" y="90.0" z="0.0"/>
    </stand>
    <stand id="stage1_normal" modification="stage1_normal_banister">
      <position x="35.0" y="0.0" z="10.0"/>
      <rotation x="0.0" y="90.0" z="0.0"/>
    </stand>
    <stand id="stage1_curve" modification="stage1_curve_banister">
      <position x="35.0" y="0.0" z="25.0"/>
      <rotation x="0.0" y="0.0" z="0.0"/>
    </stand>
    <stand id="stage1_completion" modification="stage1_completion_round_r">
      <position x="-50.0" y="0.0" z="5.0"/>
      <rotation x="0.0" y="180.0" z="0.0"/>
    </stand>
    <stand id="stage1_completion" modification="stage1_completion_round_l">
      <position x="-50.0" y="0.0" z="-5.0"/>
      <rotation x="0.0" y="0.0" z="0.0"/>
    </stand>
    <stand id="stage1_normal" modification="stage1_normal_stairs_r">
      <position x="-35.0" y="0.0" z="-10.0"/>
      <rotation x="0.0" y="270.0" z="0.0"/>
    </stand>
    <stand id="stage1_normal" modification="stage1_normal_stairs_l">
      <position x="-35.0" y="0.0" z="10.0"/>
      <rotation x="0.0" y="270.0" z="0.0"/>
    </stand>
    <stand id="stage1_normal" modification="stage1_normal">
      <position x="20.0" y="0.0" z="25.0"/>
      <rotation x="0.0" y="0.0" z="0.0"/>
    </stand>
  </stands>
  <adboards>
    <adboard id="adboard1">
      <position x="-12.0" y="0.0" z="15.0"/>
      <rotation x="0.0" y="0.0" z="0.0"/>
    </adboard>
    <adboard id="adboard3">
      <position x="-23.0" y="0.0" z="12.0"/>
      <rotation x="0.0" y="315.0" z="0.0"/>
    </adboard>
    <adboard id="adboard4">
      <position x="-25.0" y="0.0" z="2.0"/>
      <rotation x="0.0" y="270.0" z="0.0"/>
    </adboard>
    <adboard id="adboard2">
      <position x="12.0" y="0.0" z="12.0"/>
      <rotation x="0.0" y="0.0" z="0.0"/>
    </adboard>
    <adboard id="adboard3">
      <position x="21.0" y="0.0" z="14.0"/>
      <rotation x="0.0" y="30.0" z="0.0"/>
    </adboard>
    <adboard id="adboard2">
      <position x="25.0" y="0.0" z="6.0"/>
      <rotation x="0.0" y="90.0" z="0.0"/>
    </adboard>
    <adboard id="adboard4">
      <position x="25.0" y="0.0" z="-3.0"/>
      <rotation x="0.0" y="90.0" z="0.0"/>
    </adboard>
    <adboard id="adboard2">
      <position x="-24.0" y="0.0" z="-8.0"/>
      <rotation x="0.0" y="255.0" z="0.0"/>
    </adboard>
    <adboard id="adboard3">
      <position x="-17.0" y="0.0" z="-15.0"/>
      <rotation x="0.0" y="195.0" z="0.0"/>
    </adboard>
    <adboard id="adboard4">
      <position x="-8.0" y="0.0" z="-16.0"/>
      <rotation x="0.0" y="180.0" z="0.0"/>
    </adboard>
    <adboard id="adboard3">
      <position x="2.0" y="0.0" z="-16.0"/>
      <rotation x="0.0" y="180.0" z="0.0"/>
    </adboard>
    <adboard id="adboard1">
      <position x="11.0" y="0.0" z="-16.0"/>
      <rotation x="0.0" y="180.0" z="0.0"/>
    </adboard>
    <adboard id="adboard2">
      <position x="21.0" y="0.0" z="-12.0"/>
      <rotation x="0.0" y="135.0" z="0.0"/>
    </adboard>
  </adboards>
  <scoreboard stage="2">
    <position x="25.0" y="0.0" z="15.0"/>
    <rotation x="0.0" y="60.0" z="0.0"/>
  </scoreboard>
  <floodlights>
    <floodlight stage="2">
      <position x="32.0" y="0.0" z="21.0"/>
      <rotation x="0.0" y="225.0" z="0.0"/>
    </floodlight>
    <floodlight stage="2">
      <position x="32.0" y="0.0" z="-21.0"/>
      <rotation x="0.0" y="315.0" z="0.0"/>
    </floodlight>
    <floodlight stage="2">
      <position x="-31.0" y="0.0" z="21.0"/>
      <rotation x="0.0" y="135.0" z="0.0"/>
    </floodlight>
    <floodlight stage="2">
      <position x="-30.0" y="0.0" z="-21.0"/>
      <rotation x="0.0" y="45.0" z="0.0"/>
    </floodlight>
  </floodlights>
  <attractions>
    <hotdogstand>
      <position x="14.0" y="6.0" z="30.0"/>
      <rotation x="0.0" y="255.0" z="0.0"/>
    </hotdogstand>
    <beerbar>
      <position x="-25.0" y="0.0" z="-15.0"/>
      <rotation x="0.0" y="240.0" z="0.0"/>
    </beerbar>
    <highjump>
      <position x="25.0" y="0.0" z="-16.0"/>
      <rotation x="0.0" y="30.0" z="0.0"/>
    </highjump>
  </attractions>
  <objects>
    <object id="fence.x">
      <position x="-22.0" y="0.0" z="17.0"/>
      <rotation x="0.0" y="0.0" z="0.0"/>
    </object>
    <object id="fence.x">
      <position x="-17.0" y="0.0" z="17.0"/>
      <rotation x="0.0" y="0.0" z="0.0"/>
    </object>
    <object id="fence.x">
      <position x="-12.0" y="0.0" z="17.0"/>
      <rotation x="0.0" y="0.0" z="0.0"/>
    </object>
    <object id="banner.x">
      <position x="-22.0" y="0.0" z="17.0"/>
      <rotation x="0.0" y="0.0" z="0.0"/>
    </object>
    <object id="banner.x">
      <position x="-17.0" y="0.0" z="17.0"/>
      <rotation x="0.0" y="0.0" z="0.0"/>
    </object>
    <object id="banner.x">
      <position x="-12.0" y="1.0" z="17.0"/>
      <rotation x="0.0" y="0.0" z="0.0"/>
    </object>
    <object id="fence.x">
      <position x="-26.0" y="0.0" z="15.0"/>
      <rotation x="0.0" y="315.0" z="0.0"/>
    </object>
    <object id="fence.x">
      <position x="-28.0" y="0.0" z="11.0"/>
      <rotation x="0.0" y="270.0" z="0.0"/>
    </object>
    <object id="fence.x">
      <position x="-28.0" y="0.0" z="6.0"/>
      <rotation x="0.0" y="270.0" z="0.0"/>
    </object>
    <object id="banner.x">
      <position x="-28.0" y="0.0" z="6.0"/>
      <rotation x="0.0" y="270.0" z="0.0"/>
    </object>
    <object id="banner.x">
      <position x="-28.0" y="1.0" z="11.0"/>
      <rotation x="0.0" y="270.0" z="0.0"/>
    </object>
    <object id="banner.x">
      <position x="-26.0" y="1.0" z="15.0"/>
      <rotation x="0.0" y="315.0" z="0.0"/>
    </object>
    <object id="beerbar.x">
      <position x="-44.0" y="6.0" z="0.0"/>
      <rotation x="0.0" y="105.0" z="0.0"/>
    </object>
    <object id="beerbar.x">
      <position x="12.0" y="-0.5299998" z="20.0"/>
      <rotation x="0.0" y="30.0" z="0.0"/>
    </object>
    <object id="beerbar.x">
      <position x="29.66999" y="-0.3999999" z="-10.719994"/>
      <rotation x="0.0" y="60.0" z="0.0"/>
    </object>
    <object id="beerbar.x">
      <position x="-20.0" y="6.0" z="43.0"/>
      <rotation x="0.0" y="0.0" z="0.0"/>
    </object>
    <object id="beerbar.x">
      <position x="20.0" y="6.0" z="42.0"/>
      <rotation x="0.0" y="195.0" z="0.0"/>
    </object>
    <object id="tree4.x">
      <position x="-14.0" y="11.0" z="-39.0"/>
      <rotation x="0.0" y="315.0" z="0.0"/>
    </object>
    <object id="tree4.x">
      <position x="0.0" y="11.0" z="-39.0"/>
      <rotation x="0.0" y="315.0" z="0.0"/>
    </object>
    <object id="tree4.x">
      <position x="14.0" y="11.0" z="-39.0"/>
      <rotation x="0.0" y="315.0" z="0.0"/>
    </object>
  </objects>
</stadium>
